<Properties StartupConfiguration="{0AF68CBF-0AAA-4BCA-88A4-9B6BB3B1126D}|">
  <MonoDevelop.Ide.Workbench ActiveDocument="Assets/ColorizeCountries.cs">
    <Files>
      <File FileName="Assets/ColorizeCountries.cs" Line="40" Column="52" />
    </Files>
    <Pads>
      <Pad Id="ProjectPad">
        <State name="__root__">
          <Node name="VALENTINE" expanded="True" selected="True" />
        </State>
      </Pad>
    </Pads>
  </MonoDevelop.Ide.Workbench>
  <MonoDevelop.Ide.DebuggingService.PinnedWatches />
  <MonoDevelop.Ide.Workspace ActiveConfiguration="Debug" />
  <MonoDevelop.Ide.ItemProperties.Assembly-CSharp PreferredExecutionTarget="f6dce629-0fa6-4a69-b6a7-a3349c40086b" />
  <MonoDevelop.Ide.DebuggingService.Breakpoints>
    <BreakpointStore />
  </MonoDevelop.Ide.DebuggingService.Breakpoints>
  <MultiItemStartupConfigurations />
</Properties>